vuldetectbench/__init__.py
vuldetectbench/generation/__init__.py
vuldetectbench/generation/generation.py
vuldetectbench/prompt/__init__.py
vuldetectbench/prompt/templates.py
vuldetectbench/task/__init__.py
vuldetectbench/task/key_obj_func_detect.py
vuldetectbench/task/trigger_point_root_cause_detect.py
vuldetectbench/task/vul_existence.py
vuldetectbench/task/vul_type_cls.py
vuldetectbench/utils/__init__.py
vuldetectbench/utils/metrics.py
vuldetectbench-0.0.5.dist-info/METADATA
vuldetectbench-0.0.5.dist-info/WHEEL
vuldetectbench-0.0.5.dist-info/top_level.txt
vuldetectbench-0.0.5.dist-info/RECORD
