Metadata-Version: 2.1
Name: vuldetectbench
Version: 0.0.5
Summary: VulDetectBench
Home-page: https://github.com/Sweetaroo/VulDetectBench
Author: Lang Gao
Author-email: vuldetectbench@gmail.com
Requires-Dist: transformers
Requires-Dist: huggingface-hub
Requires-Dist: datasets
Requires-Dist: openai >=1.0.0
Requires-Dist: tqdm
Requires-Dist: nltk
Requires-Dist: numpy
Requires-Dist: pandas
Requires-Dist: scipy
Requires-Dist: python-liquid
Requires-Dist: requests
